odoo_rpc_helper/__init__.py
odoo_rpc_helper/rpc_helpers.py
odoo_rpc_helper/test.py
odoo_rpc_helper-0.0.7.dist-info/LICENSE
odoo_rpc_helper-0.0.7.dist-info/METADATA
odoo_rpc_helper-0.0.7.dist-info/WHEEL
odoo_rpc_helper-0.0.7.dist-info/top_level.txt
odoo_rpc_helper-0.0.7.dist-info/RECORD
