Metadata-Version: 2.1
Name: odoo-rpc-helper
Version: 0.0.7
Summary: A simple wrapper for more easily running Odoo RPC commands.
Home-page: https://github.com/bemade/odoo_rpc_helper
Author: Marc Durepos
Author-email: marc@bemade.org
License: MIT
Keywords: odoo rpc xmlrpc
License-File: LICENSE
